management_api_tools/__init__.py
management_api_tools/api/__init__.py
management_api_tools/api/metrics.py
management_api_tools/api/policies.py
management_api_tools/utils/__init__.py
management_api_tools/utils/auth.py
management_api_tools-1.0.0.dist-info/METADATA
management_api_tools-1.0.0.dist-info/WHEEL
management_api_tools-1.0.0.dist-info/top_level.txt
management_api_tools-1.0.0.dist-info/RECORD
