Metadata-Version: 2.1
Name: management-api-tools
Version: 1.0.0
Summary: Python SDK for Machina Management API's
Home-page: https://github.com/Fauxsys/management_api_tools
Author: Steven Cassamajor
Author-email: contributor@networkaxis.org
License: UNKNOWN
Project-URL: Documentation, https://dev.ionic.com/api/
Platform: UNKNOWN
Classifier: Intended Audience :: Developers
Classifier: License :: OSI Approved :: MIT License
Classifier: Programming Language :: Python :: 3
Requires-Python: >=3.7
Requires-Dist: requests
Provides-Extra: test
Requires-Dist: pytest ; extra == 'test'
Requires-Dist: pytest-cov ; extra == 'test'
Requires-Dist: tox ; extra == 'test'
Requires-Dist: parserconfig ; extra == 'test'
